yeedu/__init__.py
yeedu/config.py
yeedu/constants.py
yeedu/yeedu.py
yeedu/openapi/__init__.py
yeedu/openapi/cluster/__init__.py
yeedu/openapi/cluster/cluster_configuration.py
yeedu/openapi/cluster/cluster_instance.py
yeedu/openapi/cluster/cluster_workspace_mapping.py
yeedu/openapi/cluster/download_cluster_instance_logs.py
yeedu/openapi/configure/__init__.py
yeedu/openapi/configure/configure_user.py
yeedu/openapi/iam/__init__.py
yeedu/openapi/iam/common_platform_and_admin.py
yeedu/openapi/iam/iam_lookup.py
yeedu/openapi/iam/platform_admin.py
yeedu/openapi/iam/shared_platform_and_admin.py
yeedu/openapi/iam/user.py
yeedu/openapi/job/__init__.py
yeedu/openapi/job/download_job_instance_logs.py
yeedu/openapi/job/spark_job_config.py
yeedu/openapi/job/spark_job_instance.py
yeedu/openapi/notebook/__init__.py
yeedu/openapi/notebook/download_notebook_instance_logs.py
yeedu/openapi/notebook/notebook_config.py
yeedu/openapi/notebook/notebook_instance.py
yeedu/openapi/resource/__init__.py
yeedu/openapi/resource/boot_disk_image_configuration.py
yeedu/openapi/resource/cloud_environment.py
yeedu/openapi/resource/credentials_config.py
yeedu/openapi/resource/hive_metastore_configuration.py
yeedu/openapi/resource/lookup.py
yeedu/openapi/resource/network_configuration.py
yeedu/openapi/resource/object_storage_manager.py
yeedu/openapi/resource/object_storage_manager_files.py
yeedu/openapi/resource/volume_configuration.py
yeedu/openapi/workspace/__init__.py
yeedu/openapi/workspace/workspace.py
yeedu/openapi/workspace/workspace_access_control.py
yeedu/parsers/__init__.py
yeedu/parsers/service_parser.py
yeedu/parsers/cluster/__init__.py
yeedu/parsers/cluster/cluster_conf_parser.py
yeedu/parsers/cluster/cluster_inst_parser.py
yeedu/parsers/cluster/cluster_workspace_mapping_parser.py
yeedu/parsers/cluster/download_cluster_instance_log_parser.py
yeedu/parsers/configure/__init__.py
yeedu/parsers/configure/configure_user_parser.py
yeedu/parsers/iam/__init__.py
cli_yeedu-1.0.0.dist-info/METADATA
cli_yeedu-1.0.0.dist-info/WHEEL
cli_yeedu-1.0.0.dist-info/entry_points.txt
cli_yeedu-1.0.0.dist-info/top_level.txt
cli_yeedu-1.0.0.dist-info/RECORD
